[
    {
      "questionNumber": 1,
      "questionText": "Find skulpturen i nærheden af slottet",
      "imageUrl": "images/bronze-equestrian-statue-3301377_640.jpg",
      "questionSubtitle": "Hvad hedder Skulpturen?",
      "options": [
        {
          "optionLetter": "A",
          "optionText": "Pige på hest"
        },
        {
          "optionLetter": "B",
          "optionText": "Rytterstaue",
          "isCorrect": true
        },
        {
          "optionLetter": "C",
          "optionText": "Ridder"
        },
        {
          "optionLetter": "D",
          "optionText": "Pigens hest"
        }
      ]
    },
    {
      "questionNumber": 2,
      "questionText": "Tæl kanonerne omkring slottet",
      "imageUrl": "images/Kanon-ved-Sønderborg-Slot-credit-Comwell-Hotels.jpg",
      "questionSubtitle": "Hvor mange kanoner stå omkring slottet?",
      "options": [
        {
          "optionLetter": "A",
          "optionText": "3 Kanoner",
          "isCorrect": true
        },
        {
          "optionLetter": "B",
          "optionText": "5 Kanoner"
        },
        {
          "optionLetter": "C",
          "optionText": "4 Kanoner"
        },
        {
          "optionLetter": "D",
          "optionText": "0 Kanoner"
        }
      ]
    },
    {
      "questionNumber": 3,
      "questionText": "Find ud hvad der gemmer sig her",
      "imageUrl": "images/236177_Snderborg-Slot-fra-luften.webp",
      "questionSubtitle": "Hvad gemmer sig her?",
      "options": [
        {
          "optionLetter": "A",
          "optionText": "En have"
        },
        {
          "optionLetter": "B",
          "optionText": "Fangehulet",
          "isCorrect": true
        },
        {
          "optionLetter": "C",
          "optionText": "Ingeting"
        },
        {
          "optionLetter": "D",
          "optionText": "En Skulptur"
        }
      ]
    },
    {
      "questionNumber": 4,
      "questionText": "Tæl vinduerne på bagsiden",
      "imageUrl": "images/sonderborg_©Daniel Villadsen.jpg",
      "questionSubtitle": "Hvor mange vinduer er der?",
      "options": [
        {
          "optionLetter": "A",
          "optionText": "22 vinduer"
        },
        {
          "optionLetter": "B",
          "optionText": "0 vinduer"
        },
        {
          "optionLetter": "C",
          "optionText": "21 vinduer",
          "isCorrect": true
        },
        {
          "optionLetter": "D",
          "optionText": "10 vinduer"
        }
      ]
    },
    {
      "questionNumber": 5,
      "questionText": "Find ud hvor mange dør der er ved indgangen",
      "imageUrl": "images/236177_Snderborg-Slot-fra-luften.webp",
      "questionSubtitle": "Hvor mange dør er der?",
      "options": [
        {
          "optionLetter": "A",
          "optionText": "2 Dør"
        },
        {
          "optionLetter": "B",
          "optionText": "3 Dør"
        },
        {
          "optionLetter": "C",
          "optionText": "0 Dør"
        },
        {
          "optionLetter": "D",
          "optionText": "1 Dør",
          "isCorrect": true
        }
      ]
    }
  ]